mcp_server_monday/__init__.py
mcp_server_monday/board.py
mcp_server_monday/constants.py
mcp_server_monday/fastmcp_server.py
mcp_server_monday/item.py
mcp_server_monday-0.3.0.dist-info/METADATA
mcp_server_monday-0.3.0.dist-info/WHEEL
mcp_server_monday-0.3.0.dist-info/entry_points.txt
mcp_server_monday-0.3.0.dist-info/licenses/LICENSE
mcp_server_monday-0.3.0.dist-info/RECORD
