Metadata-Version: 2.4
Name: mcp-server-monday
Version: 0.3.0
Summary: MCP Server for monday.com
Project-URL: Homepage, https://github.com/sakce/mcp-server-monday/
Author: Jovan Sakovic
License-File: LICENSE
Requires-Python: >=3.10
Requires-Dist: fastmcp>=2.11.3
Requires-Dist: mcp[cli]>=1.2.1
Requires-Dist: monday>=2.0.1
Requires-Dist: requests>=2.32.3
